nmr/__init__.py
nmr/__main__.py
nmr/_main.py
nmr/count_words.py
nmr/nmr.py
nmr/types/__init__.py
nmr/types/_type.py
nmr/types/fraction.py
nmr/types/hex.py
nmr/types/integer.py
nmr/types/ip_address.py
nmr/types/lat_long.py
nmr/types/sem_ver.py
nmr/types/times.py
nmr/types/type_groups.py
nmr/types/uuid.py
nmr-0.9.1.dist-info/LICENSE
nmr-0.9.1.dist-info/WHEEL
nmr-0.9.1.dist-info/METADATA
nmr-0.9.1.dist-info/RECORD
