Metadata-Version: 2.1
Name: nmr
Version: 0.9.1
Summary: 🔢 name all canonical things 🔢
License: MIT
Author: Tom Ritchford
Author-email: tom@swirly.com
Requires-Python: >=3.8,<4.0
Classifier: License :: OSI Approved :: MIT License
Classifier: Programming Language :: Python :: 3
Classifier: Programming Language :: Python :: 3.8
Classifier: Programming Language :: Python :: 3.9
Classifier: Programming Language :: Python :: 3.10
Classifier: Programming Language :: Python :: 3.11
Requires-Dist: chess (>=1.9.3,<2.0.0)
Requires-Dist: datacls (>=4.5.0,<5.0.0)
Requires-Dist: dtyper (>=2.0.0,<3.0.0)
Requires-Dist: lat-lon-parser (>=1.3.0,<2.0.0)
Requires-Dist: typer (>=0.7.0,<0.8.0)
Requires-Dist: xmod (>=1.3.2,<2.0.0)
